README.md
setup.py
function_controler/__init__.py
function_controler/time_ctrl.py
function_controler.egg-info/PKG-INFO
function_controler.egg-info/SOURCES.txt
function_controler.egg-info/dependency_links.txt
function_controler.egg-info/entry_points.txt
function_controler.egg-info/requires.txt
function_controler.egg-info/top_level.txt