Metadata-Version: 2.1
Name: function-controler
Version: 0.0.7
Summary: Control the maximum running time of a function.
Home-page: https://github.com/dongshuyan/function_controler
Author: sauterne
Author-email: ssauterne@qq.com
License: MIT Licence
Keywords: pip,function_controler,running time,control
Platform: any
